edu_segmentation/__init__.py
edu_segmentation/BARTTokenClassification/bart_tokenizer.py
edu_segmentation/BARTTokenClassification/config_bart.py
edu_segmentation/BARTTokenClassification/import_data_bart.py
edu_segmentation/BARTTokenClassification/model.py
edu_segmentation/BARTTokenClassification/model_dependencies/all_vocabulary.pickle
edu_segmentation/BARTTokenClassification/model_dependencies/model_bart_v2.py
edu_segmentation/BARTTokenClassification/model_dependencies/train_segbot_bart.py
edu_segmentation/BARTTokenClassification/run_segbot.py
edu_segmentation/BARTTokenClassification/run_segbot_bart.py
edu_segmentation/BARTTokenClassification/solver.py
edu_segmentation/BARTTokenClassification/solver_bart.py
edu_segmentation/BERTTokenClassification/config_bert.py
edu_segmentation/BERTTokenClassification/import_data_bert.py
edu_segmentation/BERTTokenClassification/import_data_bert_postag.py
edu_segmentation/BERTTokenClassification/postagging.py
edu_segmentation/BERTTokenClassification/postagging_new.py
edu_segmentation/BERTTokenClassification/python38bert_modelling.py
edu_segmentation/BERTTokenClassification/run_bert.py
edu_segmentation/BERTTokenClassification/solver.py
edu_segmentation/BERTTokenClassification/solver_postag.py
edu_segmentation/BERTTokenClassification/test_model.py
edu_segmentation/BERTTokenClassification/train_model.py
edu_segmentation/BERTTokenClassification/train_model_postag.py
edu_segmentation/download.py
edu_segmentation/main.py
edu_segmentation-0.0.115.dist-info/METADATA
edu_segmentation-0.0.115.dist-info/WHEEL
edu_segmentation-0.0.115.dist-info/RECORD
